{"EDITOR_STATE":{"allProjectFiles":{"bf64f0b1-4e40-47ec-b086-dc176930e7ff":{"id":"bf64f0b1-4e40-47ec-b086-dc176930e7ff","parent":null,"name":"testcommit","type":"DIRECTORY","isDirectory":true,"children":["7019cbdf-a820-4197-93df-c7137c73a735","1bdd1764-b212-4e96-b59d-7d61ef190b9b","445675ec-f6a5-4e93-a1a0-fac4b9e028b0"],"isRemovable":false,"filePath":"testcommit"},"7019cbdf-a820-4197-93df-c7137c73a735":{"id":"7019cbdf-a820-4197-93df-c7137c73a735","parent":"bf64f0b1-4e40-47ec-b086-dc176930e7ff","name":"lambda.js","type":"LAMBDA_FILE","isDirectory":false,"children":[],"isRemovable":true,"filePath":"testcommit/lambda.js","code":"exports.handler = function(event, context, callback) {\n    \n    callback(null, {\"message\": \"Successfully executed\"});\n}","triggers":[],"config":{"runtime":"nodejs8.10","timeout":60,"memory":128}},"1bdd1764-b212-4e96-b59d-7d61ef190b9b":{"id":"1bdd1764-b212-4e96-b59d-7d61ef190b9b","parent":"bf64f0b1-4e40-47ec-b086-dc176930e7ff","name":"@##$.js","type":"LAMBDA_FILE","isDirectory":false,"children":[],"isRemovable":true,"filePath":"testcommit/@##$.js","code":"exports.handler = function(event, context, callback) {\n    \n    callback(null, {\"message\": \"Successfully executed\"});\n}","triggers":[],"config":{"runtime":"nodejs8.10","timeout":60,"memory":128}},"445675ec-f6a5-4e93-a1a0-fac4b9e028b0":{"id":"445675ec-f6a5-4e93-a1a0-fac4b9e028b0","parent":"bf64f0b1-4e40-47ec-b086-dc176930e7ff","name":"@#$$test.js","type":"LAMBDA_FILE","isDirectory":false,"children":[],"isRemovable":true,"filePath":"testcommit/@#$$test.js","code":"exports.handler = function(event, context, callback) {\n    \n    callback(null, {\"message\": \"Successfully executed\"});\n}","triggers":[],"config":{"runtime":"nodejs8.10","timeout":60,"memory":128}}},"deletedFiles":[],"rootNode":"bf64f0b1-4e40-47ec-b086-dc176930e7ff","openFiles":["7019cbdf-a820-4197-93df-c7137c73a735","1bdd1764-b212-4e96-b59d-7d61ef190b9b","445675ec-f6a5-4e93-a1a0-fac4b9e028b0"],"currentFileId":"445675ec-f6a5-4e93-a1a0-fac4b9e028b0","resources":{},"envVariables":[{"lambdaId":"all","varKey":"SIGMA_AWS_ACC_ID","varValue":null,"shouldPersist":false,"displayOnly":false,"editable":false}],"packageJSON":{"dependencies":{}},"lambdaId":"7019cbdf-a820-4197-93df-c7137c73a735"},"PROJECT_META":{"projectName":"testcommit","projectDescription":"","projectVersion":"1.0.0","projectRegion":"us-east-1","platform":"AWS","lastSave":1542103784617},"VCS_STATE":{"provider":"GitHub","repo":{"name":"testcommitnewrepo","url":"https://github.com/Kumudikatest/testcommitnewrepo"}}}